{"filename":"c:\\Users\\punko\\Downloads\\PoSeeReview\\__azurite_db_blob__.json","collections":[{"name":"$SERVICES_COLLECTION$","data":[],"idIndex":null,"binaryIndices":{},"constraints":null,"uniqueNames":["accountName"],"transforms":{},"objType":"$SERVICES_COLLECTION$","dirty":false,"cachedIndex":null,"cachedBinaryIndex":null,"cachedData":null,"adaptiveBinaryIndices":true,"transactional":false,"cloneObjects":false,"cloneMethod":"parse-stringify","asyncListeners":false,"disableMeta":false,"disableChangesApi":true,"disableDeltaChangesApi":true,"autoupdate":false,"serializableIndices":true,"disableFreeze":true,"ttl":null,"maxId":0,"DynamicViews":[],"events":{"insert":[],"update":[],"pre-insert":[],"pre-update":[],"close":[],"flushbuffer":[],"error":[],"delete":[null],"warning":[null]},"changes":[],"dirtyIds":[]},{"name":"$CONTAINERS_COLLECTION$","data":[{"accountName":"devstoreaccount1","name":"comics","properties":{"etag":"\"0x264740BB5E2D940\"","lastModified":"2025-11-06T21:45:39.932Z","leaseStatus":"unlocked","leaseState":"available","hasImmutabilityPolicy":false,"hasLegalHold":false,"publicAccess":"blob"},"meta":{"revision":1,"created":1762306305616,"version":0,"updated":1762465539933},"$loki":1,"containerAcl":[]}],"idIndex":null,"binaryIndices":{"accountName":{"name":"accountName","dirty":false,"values":[0]},"name":{"name":"name","dirty":false,"values":[0]}},"constraints":null,"uniqueNames":[],"transforms":{},"objType":"$CONTAINERS_COLLECTION$","dirty":false,"cachedIndex":null,"cachedBinaryIndex":null,"cachedData":null,"adaptiveBinaryIndices":true,"transactional":false,"cloneObjects":false,"cloneMethod":"parse-stringify","asyncListeners":false,"disableMeta":false,"disableChangesApi":true,"disableDeltaChangesApi":true,"autoupdate":false,"serializableIndices":true,"disableFreeze":true,"ttl":null,"maxId":1,"DynamicViews":[],"events":{"insert":[],"update":[],"pre-insert":[],"pre-update":[],"close":[],"flushbuffer":[],"error":[],"delete":[null],"warning":[null]},"changes":[],"dirtyIds":[]},{"name":"$BLOBS_COLLECTION$","data":[{"deleted":false,"accountName":"devstoreaccount1","containerName":"comics","name":"b18361cf-e11b-44bf-92f5-440f2432c775.png","properties":{"creationTime":"2025-11-06T18:32:02.728Z","lastModified":"2025-11-06T18:32:02.728Z","etag":"\"0x2594A9198EFBCC0\"","contentLength":5525356,"contentType":"image/png","contentMD5":{"type":"Buffer","data":[76,3,19,231,114,42,85,31,240,174,241,223,14,23,174,6]},"blobType":"BlockBlob","leaseStatus":"unlocked","leaseState":"available","serverEncrypted":true,"accessTier":"Hot","accessTierInferred":true,"accessTierChangeTime":"2025-11-06T18:32:02.728Z"},"snapshot":"","isCommitted":true,"persistency":{"id":"7fe37918-807c-4d28-8115-93c8cb3d0c63","offset":0,"count":5525356},"meta":{"revision":0,"created":1762453922770,"version":0},"$loki":199},{"deleted":false,"accountName":"devstoreaccount1","containerName":"comics","name":"39994f8d-7828-4005-8c84-843071b4feb1.png","properties":{"creationTime":"2025-11-06T18:32:02.786Z","lastModified":"2025-11-06T18:32:02.786Z","etag":"\"0x1BF88B66C9C6750\"","contentLength":5525357,"contentType":"image/png","contentMD5":{"type":"Buffer","data":[214,72,210,121,131,17,199,64,13,88,183,174,79,59,201,104]},"blobType":"BlockBlob","leaseStatus":"unlocked","leaseState":"available","serverEncrypted":true,"accessTier":"Hot","accessTierInferred":true,"accessTierChangeTime":"2025-11-06T18:32:02.786Z"},"snapshot":"","isCommitted":true,"persistency":{"id":"7fe37918-807c-4d28-8115-93c8cb3d0c63","offset":5525356,"count":5525357},"meta":{"revision":0,"created":1762453922813,"version":0},"$loki":200},{"deleted":false,"accountName":"devstoreaccount1","containerName":"comics","name":"0c870065-8175-4a99-93ab-944c9f8cf76d.png","properties":{"creationTime":"2025-11-06T18:33:03.309Z","lastModified":"2025-11-06T18:33:03.309Z","etag":"\"0x22B6E9F6AB35920\"","contentLength":5525357,"contentType":"image/png","contentMD5":{"type":"Buffer","data":[4,97,91,20,88,80,60,169,226,190,202,46,101,55,87,44]},"blobType":"BlockBlob","leaseStatus":"unlocked","leaseState":"available","serverEncrypted":true,"accessTier":"Hot","accessTierInferred":true,"accessTierChangeTime":"2025-11-06T18:33:03.309Z"},"snapshot":"","isCommitted":true,"persistency":{"id":"7fe37918-807c-4d28-8115-93c8cb3d0c63","offset":11050713,"count":5525357},"meta":{"revision":0,"created":1762453983341,"version":0},"$loki":201},{"deleted":false,"accountName":"devstoreaccount1","containerName":"comics","name":"20a9b753-7a2a-4e49-8062-d5efbdcf63c8.png","properties":{"creationTime":"2025-11-06T18:33:03.911Z","lastModified":"2025-11-06T18:33:03.911Z","etag":"\"0x245CFD1DCF4A520\"","contentLength":5525356,"contentType":"image/png","contentMD5":{"type":"Buffer","data":[0,191,63,244,135,1,118,106,232,182,248,24,143,220,152,103]},"blobType":"BlockBlob","leaseStatus":"unlocked","leaseState":"available","serverEncrypted":true,"accessTier":"Hot","accessTierInferred":true,"accessTierChangeTime":"2025-11-06T18:33:03.911Z"},"snapshot":"","isCommitted":true,"persistency":{"id":"7fe37918-807c-4d28-8115-93c8cb3d0c63","offset":16576070,"count":5525356},"meta":{"revision":0,"created":1762453983941,"version":0},"$loki":202},{"deleted":false,"accountName":"devstoreaccount1","containerName":"comics","name":"4a3097af-5940-4877-a14f-9744a590abe3.png","properties":{"creationTime":"2025-11-06T18:43:53.304Z","lastModified":"2025-11-06T18:43:53.304Z","etag":"\"0x271F49FB6213760\"","contentLength":3163292,"contentType":"image/png","contentMD5":{"type":"Buffer","data":[205,55,144,152,46,140,9,73,57,115,171,192,117,196,98,255]},"blobType":"BlockBlob","leaseStatus":"unlocked","leaseState":"available","serverEncrypted":true,"accessTier":"Hot","accessTierInferred":true,"accessTierChangeTime":"2025-11-06T18:43:53.304Z"},"snapshot":"","isCommitted":true,"persistency":{"id":"7fe37918-807c-4d28-8115-93c8cb3d0c63","offset":22101426,"count":3163292},"meta":{"revision":0,"created":1762454633319,"version":0},"$loki":203},{"deleted":false,"accountName":"devstoreaccount1","containerName":"comics","name":"e9dde379-3339-4e61-8339-e9bbb8ee7951.png","properties":{"creationTime":"2025-11-06T21:45:17.858Z","lastModified":"2025-11-06T21:45:17.858Z","etag":"\"0x233032061DD0140\"","contentLength":3163292,"contentType":"image/png","contentMD5":{"type":"Buffer","data":[53,126,56,56,41,177,73,47,62,202,123,133,120,4,106,15]},"blobType":"BlockBlob","leaseStatus":"unlocked","leaseState":"available","serverEncrypted":true,"accessTier":"Hot","accessTierInferred":true,"accessTierChangeTime":"2025-11-06T21:45:17.858Z"},"snapshot":"","isCommitted":true,"persistency":{"id":"7fe37918-807c-4d28-8115-93c8cb3d0c63","offset":25264718,"count":3163292},"meta":{"revision":0,"created":1762465517883,"version":0},"$loki":204},{"deleted":false,"accountName":"devstoreaccount1","containerName":"comics","name":"17c783e0-4135-41c6-897a-b0552ef5c8e4.png","properties":{"creationTime":"2025-11-06T21:46:15.842Z","lastModified":"2025-11-06T21:46:15.842Z","etag":"\"0x2320F7B7C2AEE60\"","contentLength":3163291,"contentType":"image/png","contentMD5":{"type":"Buffer","data":[232,2,107,69,32,87,90,180,219,77,236,168,199,247,254,3]},"blobType":"BlockBlob","leaseStatus":"unlocked","leaseState":"available","serverEncrypted":true,"accessTier":"Hot","accessTierInferred":true,"accessTierChangeTime":"2025-11-06T21:46:15.842Z"},"snapshot":"","isCommitted":true,"persistency":{"id":"7fe37918-807c-4d28-8115-93c8cb3d0c63","offset":28428010,"count":3163291},"meta":{"revision":0,"created":1762465575859,"version":0},"$loki":205},{"deleted":false,"accountName":"devstoreaccount1","containerName":"comics","name":"6d94cca8-f5d1-4073-a1ed-3c3a941f8c98.png","properties":{"creationTime":"2025-11-07T00:51:55.544Z","lastModified":"2025-11-07T00:51:55.544Z","etag":"\"0x229F7C2A5F34820\"","contentLength":3163292,"contentType":"image/png","contentMD5":{"type":"Buffer","data":[18,223,244,65,247,238,187,137,140,51,100,88,214,214,158,248]},"blobType":"BlockBlob","leaseStatus":"unlocked","leaseState":"available","serverEncrypted":true,"accessTier":"Hot","accessTierInferred":true,"accessTierChangeTime":"2025-11-07T00:51:55.544Z"},"snapshot":"","isCommitted":true,"persistency":{"id":"7fe37918-807c-4d28-8115-93c8cb3d0c63","offset":34754592,"count":3163292},"meta":{"revision":0,"created":1762476715563,"version":0},"$loki":207},{"deleted":false,"accountName":"devstoreaccount1","containerName":"comics","name":"73261bd6-ab98-413f-9461-bea1a51cfe01.png","properties":{"creationTime":"2025-11-07T23:00:56.898Z","lastModified":"2025-11-07T23:00:56.898Z","etag":"\"0x1F5DCE76952C6B0\"","contentLength":5525356,"contentType":"image/png","contentMD5":{"type":"Buffer","data":[54,138,145,176,11,220,53,254,232,198,13,58,173,204,177,40]},"blobType":"BlockBlob","leaseStatus":"unlocked","leaseState":"available","serverEncrypted":true,"accessTier":"Hot","accessTierInferred":true,"accessTierChangeTime":"2025-11-07T23:00:56.898Z"},"snapshot":"","isCommitted":true,"persistency":{"id":"7d9331e6-76c6-416b-a3c4-68232e470f65","offset":5535597,"count":5525356},"meta":{"revision":0,"created":1762556456932,"version":0},"$loki":460},{"deleted":false,"accountName":"devstoreaccount1","containerName":"comics","name":"2bcc4f61-13f5-4922-add8-ea963eac44b9.png","properties":{"creationTime":"2025-11-08T15:25:04.201Z","lastModified":"2025-11-08T15:25:04.201Z","etag":"\"0x256F2B2A3457D60\"","contentLength":3774849,"contentType":"image/png","contentMD5":{"type":"Buffer","data":[124,172,123,220,211,13,147,92,127,209,100,216,224,71,99,149]},"blobType":"BlockBlob","leaseStatus":"unlocked","leaseState":"available","serverEncrypted":true,"accessTier":"Hot","accessTierInferred":true,"accessTierChangeTime":"2025-11-08T15:25:04.201Z"},"snapshot":"","isCommitted":true,"persistency":{"id":"30f4c53e-7737-4880-8ea7-cb1e334caefb","offset":0,"count":3774849},"meta":{"revision":0,"created":1762615504253,"version":0},"$loki":482},{"deleted":false,"accountName":"devstoreaccount1","containerName":"comics","name":"5a53f0d5-227a-4562-be8f-810350b4b621.png","properties":{"creationTime":"2025-11-08T15:51:46.742Z","lastModified":"2025-11-08T15:51:46.742Z","etag":"\"0x22D3307B12AC0C0\"","contentLength":3221202,"contentType":"image/png","contentMD5":{"type":"Buffer","data":[7,113,134,60,229,236,151,92,49,195,156,213,111,201,43,135]},"blobType":"BlockBlob","leaseStatus":"unlocked","leaseState":"available","serverEncrypted":true,"accessTier":"Hot","accessTierInferred":true,"accessTierChangeTime":"2025-11-08T15:51:46.742Z"},"snapshot":"","isCommitted":true,"persistency":{"id":"30f4c53e-7737-4880-8ea7-cb1e334caefb","offset":13516137,"count":3221202},"meta":{"revision":0,"created":1762617106761,"version":0},"$loki":486},{"deleted":false,"accountName":"devstoreaccount1","containerName":"comics","name":"7a970d0e-d999-4254-8090-312b919c076f.png","properties":{"creationTime":"2025-11-12T14:03:12.440Z","lastModified":"2025-11-12T14:03:12.440Z","etag":"\"0x1E12522AF9E2270\"","contentLength":1854174,"contentType":"image/png","contentMD5":{"type":"Buffer","data":[135,74,38,213,139,177,220,19,237,118,70,216,188,239,158,250]},"blobType":"BlockBlob","leaseStatus":"unlocked","leaseState":"available","serverEncrypted":true,"accessTier":"Hot","accessTierInferred":true,"accessTierChangeTime":"2025-11-12T14:03:12.440Z"},"snapshot":"","isCommitted":true,"persistency":{"id":"aed056b0-c34c-491e-be0e-bc9aa8bd225e","offset":0,"count":1854174},"meta":{"revision":0,"created":1762956192459,"version":0},"$loki":488},{"deleted":false,"accountName":"devstoreaccount1","containerName":"comics","name":"d79ac148-484f-4a9f-9e37-b365e85305eb.png","properties":{"creationTime":"2025-11-12T14:03:58.403Z","lastModified":"2025-11-12T14:03:58.403Z","etag":"\"0x21B296D4D34EBC0\"","contentLength":1749634,"contentType":"image/png","contentMD5":{"type":"Buffer","data":[255,197,117,50,199,88,203,208,37,41,2,130,149,61,12,112]},"blobType":"BlockBlob","leaseStatus":"unlocked","leaseState":"available","serverEncrypted":true,"accessTier":"Hot","accessTierInferred":true,"accessTierChangeTime":"2025-11-12T14:03:58.403Z"},"snapshot":"","isCommitted":true,"persistency":{"id":"aed056b0-c34c-491e-be0e-bc9aa8bd225e","offset":1854174,"count":1749634},"meta":{"revision":0,"created":1762956238416,"version":0},"$loki":489}],"idIndex":[199,200,201,202,203,204,205,207,460,482,486,488,489],"binaryIndices":{"accountName":{"name":"accountName","dirty":false,"values":[0,1,2,3,4,5,6,7,8,9,10,11,12]},"containerName":{"name":"containerName","dirty":false,"values":[0,1,2,3,4,5,6,7,8,9,10,11,12]},"name":{"name":"name","dirty":false,"values":[2,6,3,9,1,4,10,7,8,11,0,12,5]},"snapshot":{"name":"snapshot","dirty":false,"values":[0,1,2,3,4,5,6,7,8,9,10,11,12]}},"constraints":null,"uniqueNames":[],"transforms":{},"objType":"$BLOBS_COLLECTION$","dirty":false,"cachedIndex":null,"cachedBinaryIndex":null,"cachedData":null,"adaptiveBinaryIndices":true,"transactional":false,"cloneObjects":false,"cloneMethod":"parse-stringify","asyncListeners":false,"disableMeta":false,"disableChangesApi":true,"disableDeltaChangesApi":true,"autoupdate":false,"serializableIndices":true,"disableFreeze":true,"ttl":null,"maxId":534,"DynamicViews":[],"events":{"insert":[],"update":[],"pre-insert":[],"pre-update":[],"close":[],"flushbuffer":[],"error":[],"delete":[null],"warning":[null]},"changes":[],"dirtyIds":[]},{"name":"$BLOCKS_COLLECTION$","data":[],"idIndex":null,"binaryIndices":{"accountName":{"name":"accountName","dirty":false,"values":[]},"containerName":{"name":"containerName","dirty":false,"values":[]},"blobName":{"name":"blobName","dirty":false,"values":[]},"name":{"name":"name","dirty":false,"values":[]}},"constraints":null,"uniqueNames":[],"transforms":{},"objType":"$BLOCKS_COLLECTION$","dirty":false,"cachedIndex":null,"cachedBinaryIndex":null,"cachedData":null,"adaptiveBinaryIndices":true,"transactional":false,"cloneObjects":false,"cloneMethod":"parse-stringify","asyncListeners":false,"disableMeta":false,"disableChangesApi":true,"disableDeltaChangesApi":true,"autoupdate":false,"serializableIndices":true,"disableFreeze":true,"ttl":null,"maxId":0,"DynamicViews":[],"events":{"insert":[],"update":[],"pre-insert":[],"pre-update":[],"close":[],"flushbuffer":[],"error":[],"delete":[null],"warning":[null]},"changes":[],"dirtyIds":[]}],"databaseVersion":1.5,"engineVersion":1.5,"autosave":true,"autosaveInterval":5000,"autosaveHandle":null,"throttledSaves":true,"options":{"persistenceMethod":"fs","autosave":true,"autosaveInterval":5000,"serializationMethod":"normal","destructureDelimiter":"$<\n"},"persistenceMethod":"fs","persistenceAdapter":null,"verbose":false,"events":{"init":[null],"loaded":[],"flushChanges":[],"close":[],"changes":[],"warning":[]},"ENV":"NODEJS"}